{
    "data": [
        {
            "id_categoria": "PAR",
            "categoria": "Parras",
            "id_producto": "PAR1",
            "nombre_producto": "Moscatel ",
            "medidas": "1 mt",
            "precio": 8000,
            "foto": ["./images/Parras Moscatel -Talagarden Vivero Santiago.jpg"],
            "descripcion": "Enredadera de crecimiento rapido, puede llegar a dar mucho fruto y mucha sombra en los lugares correctos.",
            "cuidados": "Requiere Sol, no necesita tanta agua y es resistente a sequias y a heladas no menores de -5 grados.",
            "luz": [1]
        },
        {
            "id_categoria": "PAR",
            "categoria": "Parras",
            "id_producto": "PAR2",
            "nombre_producto": "Sultanina ",
            "medidas": "1 mt",
            "precio": 8000,
            "foto": ["./images/Parras Sultanina -Talagarden Vivero Santiago.jpg"],
            "descripcion": "Enredadera de crecimiento rapido, puede llegar a dar mucho fruto y mucha sombra en los lugares correctos.",
            "cuidados": "Requiere Sol, no necesita tanta agua y es resistente a sequias y a heladas no menores de -5 grados.",
            "luz": [1]
        },
        {
            "id_categoria": "PAR",
            "categoria": "Parras",
            "id_producto": "PAR3",
            "nombre_producto": "Torontel",
            "medidas": "1 mt",
            "precio": 8000,
            "foto": ["./images/Parras Torontel-Talagarden Vivero Santiago.jpg"],
            "descripcion": "",
            "cuidados": "",
            "luz": []
        },
        {
            "id_categoria": "FRU",
            "categoria": "Frutales ",
            "id_producto": "FRU1",
            "nombre_producto": "Almendro",
            "medidas": "1,5 mts",
            "precio": 9000,
            "foto": ["./images/arbol de almendro -Talagarden Vivero Santiago.jpg"],
            "descripcion": "Arbol que puede llegar a medir 5 mts de alto, Una floración de las mas bonitas en primavera y da frutos en gran magnitud.",
            "cuidados": "Requiere Sol o SemiSombra, No necesita tanta agua y resiste heladas no menores de -5 grados.",
            "luz": [1, 3]
        },
        {
            "id_categoria": "FRU",
            "categoria": "Frutales ",
            "id_producto": "FRU2",
            "nombre_producto": "Arándano",
            "medidas": "60 cms",
            "precio": 8000,
            "foto": ["./images/arbol arandanos -Talagarden Vivero Santiago.jpg"],
            "descripcion": "Arbusto que puede crecer en macetero o en tierra directamente, puede dar muchos frutos, sus hojas cambian de color en invierno y le dará vida a tu jardin en ese tiempo. ",
            "cuidados": "Requiere SemiSombra para darse bien, Requiere tierra ligeramente acida y resiste las heladas no mayores a -5 grados",
            "luz": [3]
        },
        {
            "id_categoria": "FRU",
            "categoria": "Frutales ",
            "id_producto": "FRU3",
            "nombre_producto": "Caqui",
            "medidas": "1,2 mts",
            "precio": 9000,
            "foto":["./images/arbol caqui -Talagarden Vivero Santiago.jpg"],
            "descripcion": "Arbol que puede llegar a medir 4 mts, se caracteriza por dar frutos en otoño cuando ningun arbol da frutos, al llegar el otoño pierde las hojas pero sus frutos quedan en el arbol dandole un toque especial a nuestro jardin.",
            "cuidados": "Requiere semiSombra y humedad para darse correctamente. ",
            "luz": [3]
        },
        {
            "id_categoria": "FRU",
            "categoria": "Frutales ",
            "id_producto": "FRU4",
            "nombre_producto": "Cerezo",
            "medidas": "1,5 mts",
            "precio": 9000,
            "foto": ["./images/arbol cerezo -Talagarden Vivero Santiago.jpg"],
            "descripcion": "Arbol que puede llegar a medir 4 mts de altura, su floracion es muy linda.",
            "cuidados": "",
            "luz": []
        },
        {
            "id_categoria": "FRU",
            "categoria": "Frutales ",
            "id_producto": "FRU5",
            "nombre_producto": "Ciruelo",
            "medidas": "1,8 mts",
            "precio": 9000,
            "foto": ["./images/arbol ciruelo -Talagarden Vivero Santiago.jpg"],
            "descripcion": "Arbol que puede llegar a mediar 5 mts de alto, Una floración blanca en primavera y muchos frutos asegurados en verano.",
            "cuidados": "Requiere Sol o SemiSombra, No necesita tanta agua y resiste heladas no menores de -5 grados.",
            "luz": [1, 3]
        },
        {
            "id_categoria": "FRU",
            "categoria": "Frutales ",
            "id_producto": "FRU6",
            "nombre_producto": "Damasco",
            "medidas": "1,5 mts",
            "precio": 9000,
            "foto": ["./images/arbol damasco -Talagarden Vivero Santiago.jpg"],
            "descripcion": "Arbol que puede llegar a mediar 5 mts de alto, Una floración rosada en primavera y muchos frutos asegurados en verano.",
            "cuidados": "Requiere Sol o SemiSombra, No necesita tanta agua y resiste heladas no menores de -5 grados.",
            "luz": [1, 3]
        },
        {
            "id_categoria": "FRU",
            "categoria": "Frutales ",
            "id_producto": "FRU7",
            "nombre_producto": "Durazno conservero",
            "medidas": "1 mt",
            "precio": 9000,
            "foto": ["./images/arbol durazno conservero -Talagarden Vivero Santiago.jpg"],
            "descripcion": "Arbol que puede llegar a mediar 5 mts de alto, Una floración rosada en primavera y muchos frutos asegurados en verano.",
            "cuidados": "Requiere Sol o SemiSombra, No necesita tanta agua y resiste heladas no menores de -5 grados.",
            "luz": [1, 3]
        },
        {
            "id_categoria": "FRU",
            "categoria": "Frutales ",
            "id_producto": "FRU8",
            "nombre_producto": "Durazno Plátano",
            "medidas": "1 mt",
            "precio": 9000,
            "foto": ["./images/arbol durazno nectarino platano -Talagarden Vivero Santiago-.jpg"],
            "descripcion": "Arbol que puede llegar a mediar 5 mts de alto, Una floración rosada en primavera y muchos frutos asegurados en verano.",
            "cuidados": "Requiere Sol o SemiSombra, No necesita tanta agua y resiste heladas no menores de -5 grados.",
            "luz": [1, 3]
        },
        {
            "id_categoria": "FRU",
            "categoria": "Frutales ",
            "id_producto": "FRU9",
            "nombre_producto": "Feijoa",
            "medidas": "1,2 mts",
            "precio": 12000,
            "foto": ["./images/feijoa -Talagarden Vivero Santiago.jpg"],
            "descripcion": "",
            "cuidados": "",
            "luz": []
        },
        {
            "id_categoria": "FRU",
            "categoria": "Frutales ",
            "id_producto": "FRU10",
            "nombre_producto": "Granado",
            "medidas": "50 cms",
            "precio": 9000,
            "foto": ["./images/arbol granado -Talagarden Vivero Santiago.jpg"],
            "descripcion": "Arbol o Arbusto que puede crecer hasta 5 mts de alto, Sus frutos se dan en otoño.",
            "cuidados": "Requiere Sol o SemiSombra, No necesita tanta agua y resiste heladas no menores de -5 grados.",
            "luz": [1, 3]
        },
        {
            "id_categoria": "FRU",
            "categoria": "Frutales ",
            "id_producto": "FRU11",
            "nombre_producto": "Higuera",
            "medidas": "40 cms",
            "precio": 9000,
            "foto": ["./images/arbol higuera -Talagarden Vivero Santiago.jpg"],
            "descripcion": "Arbol que puede llegar a medir hasta 10 mts, Puede dar 2 tipos de frutos distintos y para dar sombra es un espectaculo.",
            "cuidados": "Requiere Sol o SemiSombra, Tambien requiere espacio a su alrededor para crecer bien, tener cuidado porque sus raices son invasivas. No necesita tanta agua y resiste heladas no menores de -5 grados.",
            "luz": [1, 3]
        },
        {
            "id_categoria": "FRU",
            "categoria": "Frutales ",
            "id_producto": "FRU12",
            "nombre_producto": "Mancaqui",
            "medidas": "1,2 mts",
            "precio": 9000,
            "foto": ["./images/arbol mancaqui -Talagarden Vivero Santiago.jpg"],
            "descripcion": "Arbol que puede llegar a medir 4 mts, se caracteriza por dar frutos en otoño cuando ningun arbol da frutos, al llegar el otoño pierde las hojas pero sus frutos quedan en el arbol dandole un toque especial a nuestro jardin.",
            "cuidados": "",
            "luz": []
        },
        {
            "id_categoria": "FRU",
            "categoria": "Frutales ",
            "id_producto": "FRU13",
            "nombre_producto": "Manzano Fuji",
            "medidas": "1,8 mts",
            "precio": 9000,
            "foto": ["./images/arbol manzano fuji -Talagarden Vivero Santiago.jpg"],
            "descripcion": "Arbol que puede llegar a mediar 5 mts de alto, Una floración rosada en primavera y muchos frutos asegurados en verano.",
            "cuidados": "Requiere Sol o SemiSombra, No necesita tanta agua y resiste heladas no menores de -5 grados.",
            "luz": [1, 3]
        },
        {
            "id_categoria": "FRU",
            "categoria": "Frutales ",
            "id_producto": "FRU14",
            "nombre_producto": "Maqui",
            "medidas": "1 mt",
            "precio": 10000,
            "foto": ["./images/arbol arandanos -Talagarden Vivero Santiago.jpg"],
            "descripcion": "Arbol Nativo que puede alcanzar los 4 mts de alto. Da pequeños frutos muy saludables.",
            "cuidados": "Requiere SemiSombra para darse bien, Requiere tierra ligeramente acida y resiste las heladas no mayores a -5 grados",
            "luz": []
        },
        {
            "id_categoria": "FRU",
            "categoria": "Frutales ",
            "id_producto": "FRU15",
            "nombre_producto": "Membrillo Champion",
            "medidas": "1,7 mts",
            "precio": 9000,
            "foto": ["./images/arbol membrillo champion -Talagarden Vivero Santiago.jpg"],
            "descripcion": "Arbol que puede llegar a mediar 5 mts de alto. ",
            "cuidados": "Requiere Sol o SemiSombra, No necesita tanta agua y resiste heladas no menores de -5 grados.",
            "luz": [1, 3]
        },
        {
            "id_categoria": "FRU",
            "categoria": "Frutales ",
            "id_producto": "FRU16",
            "nombre_producto": "Níspero",
            "medidas": "50 cms",
            "precio": 9000,
            "foto": ["./images/arbol nispero -Talagarden Vivero Santiago.jpg"],
            "descripcion": "Arbol que puede llegar a mediar 10 mts de altode crecimiento lento. ",
            "cuidados": "Requiere Sol o SemiSombra, No necesita tanta agua y resiste heladas no menores de -5 grados.",
            "luz": [1, 3]
        },
        {
            "id_categoria": "FRU",
            "categoria": "Frutales ",
            "id_producto": "FRU17",
            "nombre_producto": "Nogal",
            "medidas": "1,8 mts",
            "precio": 10000,
            "foto": ["./images/arbol nogal -Talagarden Vivero Santiago.jpg"],
            "descripcion": "Arbol que puede llegar a mediar 7 mts de alto. Da muchos frutos en verano.",
            "cuidados": "Requiere Sol o SemiSombra, Requiere espacio para crecer y cuidado con sus raices al ser un arbol grande, No necesita tanta agua y resiste heladas no menores de -5 grados.",
            "luz": [1, 3]
        },
        {
            "id_categoria": "FRU",
            "categoria": "Frutales ",
            "id_producto": "FRU18",
            "nombre_producto": "Olivo",
            "medidas": "60 cms",
            "precio": 9000,
            "foto": ["./images/arbol olivo -Talagarden Vivero Santiago.jpg"],
            "descripcion": "Arbol o arbusto Perenne, Que puede estar en maceta, que puede crecer hasta 4 mts en tierra, son arboles que pueden vivir por cientos de años y seguir dando frutos.",
            "cuidados": "Requiere Sol, No necesita tanta agua y resiste heladas no menores de -5 grados.",
            "luz": [1, 3]
        },
        {
            "id_categoria": "FRU",
            "categoria": "Frutales ",
            "id_producto": "FRU19",
            "nombre_producto": "Peral",
            "medidas": "1,8 mts",
            "precio": 9000,
            "foto": ["./images/arbol peral -Talagarden Vivero Santiago.jpg"],
            "descripcion": "Arbol que puede llegar a mediar 7 mts de alto. Su floracion es Blanca y frutos asegurados en verano.",
            "cuidados": "Requiere Sol o SemiSombra, No necesita tanta agua y resiste heladas no menores de -5 grados.",
            "luz": [1, 3]
        },
        {
            "id_categoria": "FRU",
            "categoria": "Frutales ",
            "id_producto": "FRU20",
            "nombre_producto": "Pistacho",
            "medidas": "40 cms",
            "precio": 12000,
            "foto": ["./images/arbol pistacho Talagarden Vivero Santiago.jpg"],
            "descripcion": "",
            "cuidados": "",
            "luz": []
        },
        {
            "id_categoria": "CIT",
            "categoria": "Cítricos",
            "id_producto": "CIT1",
            "nombre_producto": "Clementino",
            "medidas": "60 cms",
            "precio": 9000,
            "foto": ["./images/Citricos Clementino  -Talagarden Vivero Santiago.jpg"],
            "descripcion": "Arbol o Arbusto Perenne, Que puede estar en maceta, puede crecer hasta los 3 mts de alto en tierra.",
            "cuidados": "Requiere Sol o SemiSombra, No necesita tanta agua y resiste heladas no menores de -5 grados.",
            "luz": [1, 3]
        },
        {
            "id_categoria": "CIT",
            "categoria": "Cítricos",
            "id_producto": "CIT2",
            "nombre_producto": "Kumquat",
            "medidas": "60 cms",
            "precio": 15000,
            "foto": ["./images/Kumquat-Talagarden Vivero Santiago.JPG"],
            "descripcion": "Arbol o Arbusto Perenne, Que puede estar en maceta, puede crecer hasta los 10 mts de alto en tierra el mejor de los casos, Su fruto es de cascara dulce y al comerlo es muy rico.",
            "cuidados": "Requiere Sol o SemiSombra, No necesita tanta agua y resiste heladas no menores de -5 grados.",
            "luz": [1, 3]
        },
        {
            "id_categoria": "CIT",
            "categoria": "Cítricos",
            "id_producto": "CIT3",
            "nombre_producto": "Limequat",
            "medidas": "60 cms",
            "precio": 15000,
            "foto": ["./images/Citricos Limequat  -Talagarden Vivero Santiago.jpg"],
            "descripcion": "Arbol o Arbusto Perenne, Que puede estar en maceta, puede crecer hasta los 10 mts de alto en tierra el mejor de los casos, Su fruto es de cascara dulce e incluso se puede comer con cascara para los que le gustan las cosas acidas.",
            "cuidados": "Requiere Sol o SemiSombra, No necesita tanta agua y resiste heladas no menores de -5 grados.",
            "luz": [1, 3]
        },
        {
            "id_categoria": "CIT",
            "categoria": "Cítricos",
            "id_producto": "CIT4",
            "nombre_producto": "Limón Génova",
            "medidas": "60 cms",
            "precio": 9000,
            "foto": ["./images/Citricos Limon Genova-Talagarden Vivero Santiago.jpg"],
            "descripcion": "Arbol o Arbusto Perenne, Que puede estar en maceta, puede crecer hasta los 10 mts de alto en tierra el mejor de los casos. Su fruto es amarillo y siempre util en nuestra casa.",
            "cuidados": "Requiere Sol o SemiSombra, No necesita tanta agua y resiste heladas no menores de -5 grados.",
            "luz": [1, 3]
        },
        {
            "id_categoria": "CIT",
            "categoria": "Cítricos",
            "id_producto": "CIT5",
            "nombre_producto": "Limón Sutil",
            "medidas": "60 cms",
            "precio": 10000,
            "foto": ["./images/Citricos Limon Sutil  -Talagarden Vivero Santiago.jpg"],
            "descripcion": "Arbol o Arbusto Perenne, Que puede estar en maceta, puede crecer hasta los 5 mts de alto en tierra el mejor de los casos. Su fruto es verde y mas pequeño que el limon Sutil, puede servir para coctel.",
            "cuidados": "Requiere Sol o SemiSombra, No necesita tanta agua y resiste heladas no menores de -5 grados.",
            "luz": [1, 3]
        },
        {
            "id_categoria": "CIT",
            "categoria": "Cítricos",
            "id_producto": "CIT6",
            "nombre_producto": "Mandarino",
            "medidas": "60 cms",
            "precio": 9000,
            "foto": ["./images/Citricos Mandarino  -Talagarden Vivero Santiago.jpg"],
            "descripcion": "Arbol o Arbusto Perenne, Que puede estar en maceta, puede crecer hasta los 3 mts de alto en tierra.",
            "cuidados": "Requiere Sol o SemiSombra, No necesita tanta agua y resiste heladas no menores de -5 grados.",
            "luz": [1, 3]
        },
        {
            "id_categoria": "CIT",
            "categoria": "Cítricos",
            "id_producto": "CIT7",
            "nombre_producto": "Mandarinquat",
            "medidas": "60 cms",
            "precio": 12000,
            "foto": ["./images/Mandarinquat-Talagarden Vivero Santiago.jpg"],
            "descripcion": "Arbol o Arbusto Perenne, Que puede estar en maceta, puede crecer hasta los 3 mts de alto en tierra.",
            "cuidados": "Requiere Sol o SemiSombra, No necesita tanta agua y resiste heladas no menores de -5 grados.",
            "luz": [1, 3]
        },
        {
            "id_categoria": "CIT",
            "categoria": "Cítricos",
            "id_producto": "CIT8",
            "nombre_producto": "Naranjo Fukumoto",
            "medidas": "60 cms",
            "precio": 9000,
            "foto": ["./images/Naranjo Fukumoto -Talagarden Vivero Santiago.JPG"],
            "descripcion": "Arbol o Arbusto Perenne, Que puede estar en maceta, puede crecer hasta los 7 mts de alto en tierra el mejor de los casos. ",
            "cuidados": "Requiere Sol o SemiSombra, No necesita tanta agua y resiste heladas no menores de -5 grados.",
            "luz": [1, 3]
        },
        {
            "id_categoria": "PAL",
            "categoria": "Paltos",
            "id_producto": "PAL1",
            "nombre_producto": "Palto Hass",
            "medidas": "60 cms",
            "precio": 9000,
            "foto": ["./images/Paltos Palto Hass -Talagarden Vivero Santiago.jpg"],
            "descripcion": "",
            "cuidados": "",
            "luz": []
        },
        {
            "id_categoria": "PAL",
            "categoria": "Paltos",
            "id_producto": "PAL2",
            "nombre_producto": "Palto Negra de la Cruz",
            "medidas": "60 cms",
            "precio": 9000,
            "foto": ["./images/Palto Negra de la cruz -Talagarden Vivero Santiago.jpg"],
            "descripcion": "",
            "cuidados": "",
            "luz": []
        },
        {
            "id_categoria": "FLO",
            "categoria": "En Flor",
            "id_producto": "FLO1",
            "nombre_producto": "Ceibo",
            "medidas": "50 cms",
            "precio": 12000,
            "foto": ["./images/En Flor Ceibo  -Talagarden Vivero.jpg"],
            "descripcion": "",
            "cuidados": "",
            "luz": []
        },
        {
            "id_categoria": "FLO",
            "categoria": "En Flor",
            "id_producto": "FLO2",
            "nombre_producto": "Cerezo en flor (Japonés)",
            "medidas": "2 mts",
            "precio": 25000,
            "foto": ["./images/En Flor Cerezo en flor Japones  -Talagarden Vivero.jpg"],
            "descripcion": "",
            "cuidados": "",
            "luz":[]
        },
        {
            "id_categoria": "FLO",
            "categoria": "En Flor",
            "id_producto": "FLO3",
            "nombre_producto": "Ciruelo en flor",
            "medidas": "1,7 mts",
            "precio": 10000,
            "foto": ["./images/En Flor Ciruelo en flor  -Talagarden Vivero.jpg"],
            "descripcion": "",
            "cuidados": "",
            "luz":[]
        },
        {
            "id_categoria": "FLO",
            "categoria": "En Flor",
            "id_producto": "FLO4",
            "nombre_producto": "Crespón Fucsia",
            "medidas": "70 cms",
            "precio": 10000,
            "foto": ["./images/En Flor Crespon fucsia  -Talagarden Vivero.jpg"],
            "descripcion": "",
            "cuidados": "",
            "luz":[]
        },
        {
            "id_categoria": "FLO",
            "categoria": "En Flor",
            "id_producto": "FLO5",
            "nombre_producto": "Durazno en flor (blanco o rosado)",
            "medidas": "1,3 mts",
            "precio": 10000,
            "foto": ["./images/En Flor Durazno en flor  -Talagarden Vivero.jpg"],
            "descripcion": "",
            "cuidados": "",
            "luz":[]
        },
        {
            "id_categoria": "FLO",
            "categoria": "En Flor",
            "id_producto": "FLO6",
            "nombre_producto": "Granado en flor",
            "medidas": "50 cms",
            "precio": 9000,
            "foto": ["./images/En Flor Granado en flor  -Talagarden Vivero.jpg"],
            "descripcion": "",
            "cuidados": "",
            "luz":[]
        },
        {
            "id_categoria": "FLO",
            "categoria": "En Flor",
            "id_producto": "FLO7",
            "nombre_producto": "Magnolia Grandiflora",
            "medidas": "1,2 mts",
            "precio": 15000,
            "foto": ["./images/Magnolia Grandiflora - Talagarden Vivero Santiago.jpg"],
            "descripcion": "Margolia es una…",
            "cuidados": "",
            "luz":[]
        },
        {
            "id_categoria": "FLO",
            "categoria": "En Flor",
            "id_producto": "FLO8",
            "nombre_producto": "Magnolia Soulangeana",
            "medidas": "1 mt",
            "precio": 20000,
            "foto": ["./images/En Flor Magnolia Soulangeana  -Talagarden Vivero.jpg"],
            "descripcion": "",
            "cuidados": "",
            "luz":[]
        },
        {
            "id_categoria": "VA",
            "categoria": "Varios",
            "id_producto": "VA1",
            "nombre_producto": "Acer Japónico",
            "medidas": "1,5 mts",
            "precio": 12000,
            "foto": ["./images/Varios Acer japones -Talagarden Vivero Santiago.jpg"],
            "descripcion": "",
            "cuidados": "",
            "luz":[]
        },
        {
            "id_categoria": "VA",
            "categoria": "Varios",
            "id_producto": "VA2",
            "nombre_producto": "Fresno",
            "medidas": "1,8 mts",
            "precio": 10000,
            "foto": ["./images/Varios Fresno -Talagarden Vivero Santiago.jpg"],
            "descripcion": "",
            "cuidados": "",
            "luz":[]
        },
        {
            "id_categoria": "VA",
            "categoria": "Varios",
            "id_producto": "VA3",
            "nombre_producto": "Laurel de comer",
            "medidas": "1,2 mts",
            "precio": 12000,
            "foto": ["./images/Varios Laurel de comer -Talagarden Vivero Santiago.jpg"],
            "descripcion": "",
            "cuidados": "",
            "luz":[]
        },
        {
            "id_categoria": "VA",
            "categoria": "Varios",
            "id_producto": "VA4",
            "nombre_producto": "Liquidambar",
            "medidas": "1,6 mts",
            "precio": 15000,
            "foto": ["./images/Varios Liquidambar -Talagarden Vivero Santiago.jpg"],
            "descripcion": "",
            "cuidados": "",
            "luz":[]
        },
        {
            "id_categoria": "VA",
            "categoria": "Varios",
            "id_producto": "VA5",
            "nombre_producto": "Pino Azul",
            "medidas": "40 cms",
            "precio": 10000,
            "foto": ["./images/Pino azul -Talagarden Vivero Santiago.jpg"],
            "descripcion": "",
            "cuidados": "",
            "luz":[]
        },
        {
            "id_categoria": "VA",
            "categoria": "Varios",
            "id_producto": "VA6",
            "nombre_producto": "Tulipero",
            "medidas": "1,6 mts",
            "precio": 15000,
            "foto": ["./images/Varios Tulipero -Talagarden Vivero Santiago.jpg"],
            "descripcion": "",
            "cuidados": "",
            "luz":[]
        },
        {
            "id_categoria": "NA",
            "categoria": "Nativos",
            "id_producto": "NA1",
            "nombre_producto": "Peumo",
            "medidas": "1,8 mts",
            "precio": 30000,
            "foto": ["./images/Peumo -Talagarden Vivero Santiago.jpg"],
            "descripcion": "Árbol nativo puede alcanzar los 30 mts de alto, De raiz Pivotante",
            "cuidados": "Requiere Sol, puede resistir heladas y cuando es adulto resiste tiempos de sequia.",
            "luz": [1]
        },
        {
            "id_categoria": "NA",
            "categoria": "Nativos",
            "id_producto": "NA2",
            "nombre_producto": "Canelo",
            "medidas": "1 mt",
            "precio": 12000,
            "foto": ["./images/Canelo -Talagarden Vivero Santiago.jpg"],
            "descripcion": "",
            "cuidados": "",
            "luz":[]
        },
        {
            "id_categoria": "NA",
            "categoria": "Nativos",
            "id_producto": "NA3",
            "nombre_producto": "Belloto del Norte",
            "medidas": "1,2 mts",
            "precio": 12000,
            "foto": ["./images/Belloto del norte -Talagarden Vivero Santiago.jpg"],
            "descripcion": "",
            "cuidados": "",
            "luz":[]
        },
        {
            "id_categoria": "NA",
            "categoria": "Nativos",
            "id_producto": "NA4",
            "nombre_producto": "Quillay",
            "medidas": "1,2 mts",
            "precio": 12000,
            "foto": ["./images/Quillay -Talagarden Vivero Santiago.jpg"],
            "descripcion": "",
            "cuidados": "",
            "luz":[]
        },
        {
            "id_categoria": "NA",
            "categoria": "Nativos",
            "id_producto": "NA5",
            "nombre_producto": "Quebracho",
            "medidas": "1 mt",
            "precio": 10000,
            "foto": ["./images/Araucana -Talagarden Vivero Santiago.jpg"],
            "descripcion": "",
            "cuidados": "",
            "luz":[]
        },
        {
            "id_categoria": "NA",
            "categoria": "Nativos",
            "id_producto": "NA6",
            "nombre_producto": "Huingan",
            "medidas": "1,2 mts",
            "precio": 12000,
            "foto": ["./images/Huingan -Talagarden Vivero Santiago.jpg"],
            "descripcion": "",
            "cuidados": "",
            "luz":[]
        },
        {
            "id_categoria": "AR",
            "categoria": "Arbustos",
            "id_producto": "AR1",
            "nombre_producto": "Boj ",
            "medidas": "1 mt",
            "precio": 15000,
            "foto": ["./images/arbusto-horizontal.jpg"],
            "descripcion": "Los Boj son…",
            "cuidados": "",
            "luz":[]
        },
        {
            "id_categoria": "AR",
            "categoria": "Arbustos",
            "id_producto": "AR2",
            "nombre_producto": "Bugambilia",
            "medidas": "80 cms",
            "precio": 12000,
            "foto": ["./images/Arbustos Bugambilia  -Talagarden Vivero Santiago.jpg"],
            "descripcion": "",
            "cuidados": "",
            "luz":[]
        },
        {
            "id_categoria": "AR",
            "categoria": "Arbustos",
            "id_producto": "AR3",
            "nombre_producto": "Corona del Poeta",
            "medidas": "1 mt",
            "precio": 10000,
            "foto": ["./images/Arbustos Corona de Poeta  -Talagarden Vivero Santiago.jpg"],
            "descripcion": "",
            "cuidados": "",
            "luz":[]
        },
        {
            "id_categoria": "AR",
            "categoria": "Arbustos",
            "id_producto": "AR4",
            "nombre_producto": "Laurentina",
            "medidas": "50 cms",
            "precio": 7000,
            "foto": ["./images/Arbustos Laurentina  -Talagarden Vivero Santiago.jpg"],
            "descripcion": "",
            "cuidados": "",
            "luz":[]
        },
        {
            "id_categoria": "AR",
            "categoria": "Arbustos",
            "id_producto": "AR5",
            "nombre_producto": "Mascantha",
            "medidas": "1 mt",
            "precio": 15000,
            "foto": ["./images/Arbustos Mascantha  -Talagarden Vivero Santiago.jpg"],
            "descripcion": "",
            "cuidados": "",
            "luz":[]
        },
        {
            "id_categoria": "AR",
            "categoria": "Arbustos",
            "id_producto": "AR6",
            "nombre_producto": "Nandina",
            "medidas": "60 cms",
            "precio": 10000,
            "foto": ["./images/Arbustos Nandina  -Talagarden Vivero Santiago.jpg"],
            "descripcion": "",
            "cuidados": "",
            "luz":[]
        },
        {
            "id_categoria": "AR",
            "categoria": "Arbustos",
            "id_producto": "AR7",
            "nombre_producto": "Pitosporo Nigricans",
            "medidas": "1,8 mts",
            "precio": 10000,
            "foto": ["./images/Arbustos Pitosporo Nigricans  -Talagarden Vivero Santiago.jpg"],
            "descripcion": "Estos arbustos son…",
            "cuidados": "",
            "luz":[]
        },
        {
            "id_categoria": "PLAN",
            "categoria": "Plantas",
            "id_producto": "PLA1",
            "nombre_producto": "Camelia",
            "medidas": "1 mt",
            "precio": 25000,
            "foto": ["./images/Camelia -Talagarden Vivero Santiago.jpg"],
            "descripcion": "Las hermosas Camelias…",
            "cuidados": "",
            "luz":[]
        },
        {
            "id_categoria": "PLAN",
            "categoria": "Plantas",
            "id_producto": "PLA2",
            "nombre_producto": "Ficus Lyrata",
            "medidas": "20 cms",
            "precio": 15000,
            "foto": ["./images/Plantas Ficus Lyrata  -Talagarden Vivero Santiago.jpg"],
            "descripcion": "",
            "cuidados": "",
            "luz":[]
        },
        {
            "id_categoria": "PLAN",
            "categoria": "Plantas",
            "id_producto": "PLA3",
            "nombre_producto": "Flor del Pájaro",
            "medidas": "30 cms",
            "precio": 6000,
            "foto": ["./images/Plantas Flor del Pajaro  -Talagarden Vivero Santiago.jpg"],
            "descripcion": "",
            "cuidados": "",
            "luz":[]
        },
        {
            "id_categoria": "PLAN",
            "categoria": "Plantas",
            "id_producto": "PLA4",
            "nombre_producto": "Hortensia",
            "medidas": "30 cms",
            "precio": 8000,
            "foto": ["images/Plantas Hortensia  -Talagarden Vivero Santiago.jpg"],
            "descripcion": "",
            "cuidados": "",
            "luz":[]
        },
        {
            "id_categoria": "PLAN",
            "categoria": "Plantas",
            "id_producto": "PLA5",
            "nombre_producto": "Monstera",
            "medidas": "30 cms",
            "precio": 10000,
            "foto": ["./images/Plantas Monstera  -Talagarden Vivero Santiago.jpg"],
            "descripcion": "",
            "cuidados": "",
            "luz":[]
        },
        {
            "id_categoria": "PLAN",
            "categoria": "Plantas",
            "id_producto": "PLA6",
            "nombre_producto": "Palmera de interior",
            "medidas": "30 cms",
            "precio": 10000,
            "foto": ["./images/Plantas Palmera Interior  -Talagarden Vivero Santiago.jpg"],
            "descripcion": "",
            "cuidados": "",
            "luz":[]
        },
        {
            "id_categoria": "PLAN",
            "categoria": "Plantas",
            "id_producto": "PLA7",
            "nombre_producto": "Sansevieria",
            "medidas": "20 cms",
            "precio": 15000,
            "foto": ["./images/Plantas Sansevieria  -Talagarden Vivero Santiago.jpg"],
            "descripcion": "",
            "cuidados": "",
            "luz":[]
        },
        {
            "id_categoria": "ROS",
            "categoria": "Rosas",
            "id_producto": "RO1",
            "nombre_producto": "Rosa Botonera",
            "medidas": "50 cms",
            "precio": 7000,
            "foto": [""],
            "descripcion": "",
            "cuidados": "",
            "luz":[]
        },
        {
            "id_categoria": "ROS",
            "categoria": "Rosas",
            "id_producto": "RO2",
            "nombre_producto": "Rosa Trepdora",
            "medidas": "50 cms",
            "precio": 8000,
            "foto": [""],
            "descripcion": "",
            "cuidados": "",
            "luz":[]
        },
        {
            "id_categoria": "CACT",
            "categoria": "Cáctus",
            "id_producto": "CACT1",
            "nombre_producto": "Cactus varios",
            "medidas": "20 cms",
            "precio": 5000,
            "foto": [""],
            "descripcion": "",
            "cuidados": "",
            "luz":[]
        },
        {
            "id_categoria": "CACT",
            "categoria": "Cáctus",
            "id_producto": "CACT2",
            "nombre_producto": "Cerebro",
            "medidas": "20 cms",
            "precio": 5000,
            "foto": [""],
            "descripcion": "",
            "cuidados": "",
            "luz":[]
        },
        {
            "id_categoria": "CACT",
            "categoria": "Cáctus",
            "id_producto": "CACT3",
            "nombre_producto": "Orejas de Conejo",
            "medidas": "20 cms",
            "precio": 5000,
            "foto": [""],
            "descripcion": "",
            "cuidados": "",
            "luz":[]
        },
        {
            "id_categoria": "ABO",
            "categoria": "Abonos",
            "id_producto": "ABO1",
            "nombre_producto": "Hummus líquido",
            "medidas": "1,5 lt",
            "precio": 3500,
            "foto": [""],
            "descripcion": "",
            "cuidados": "",
            "luz":[]
        },
        {
            "id_categoria": "ABO",
            "categoria": "Abonos",
            "id_producto": "ABO2",
            "nombre_producto": "Quelato de Hierro",
            "medidas": "50 grs",
            "precio": 4000,
            "foto": [""],
            "descripcion": "",
            "cuidados": "",
            "luz":[]
        },
        {
            "id_categoria": "ABO",
            "categoria": "Abonos",
            "id_producto": "ABO3",
            "nombre_producto": "Saco 4 Tierras",
            "medidas": "25 kg",
            "precio": 5000,
            "foto": [""],
            "descripcion": "",
            "cuidados": "",
            "luz":[]
        }
    ]
}